errorcodes/__init__.py
errorcodes-0.0.3.dist-info/LICENSE
errorcodes-0.0.3.dist-info/METADATA
errorcodes-0.0.3.dist-info/WHEEL
errorcodes-0.0.3.dist-info/RECORD
