Metadata-Version: 2.1
Name: errorcodes
Version: 0.0.3
Summary: Library that provides utilities for defining error codes for your application.
Home-page: https://github.com/kornelijus/errorcodes
License: MIT
Author: Kornelijus Tvarijanavičius
Author-email: kornelijus@tvaria.com
Requires-Python: >=3.9,<4.0
Classifier: Development Status :: 1 - Planning
Classifier: License :: OSI Approved :: MIT License
Classifier: Programming Language :: Python :: 3
Classifier: Programming Language :: Python :: 3.9
Classifier: Programming Language :: Python :: 3.10
Classifier: Programming Language :: Python :: 3.11
Classifier: Programming Language :: Python :: 3.12
Project-URL: Repository, https://github.com/kornelijus/errorcodes
